pyarchiveit/__init__.py
pyarchiveit/api.py
pyarchiveit/exceptions.py
pyarchiveit/export.py
pyarchiveit/httpx_client.py
pyarchiveit/model_validator.py
pyarchiveit/models.py
pyarchiveit/py.typed
pyarchiveit-0.8.1.dist-info/WHEEL
pyarchiveit-0.8.1.dist-info/METADATA
pyarchiveit-0.8.1.dist-info/RECORD
