Metadata-Version: 2.4
Name: pyarchiveit
Version: 0.8.1
Summary: A Python library to interact with the Archive-It's API
Author: Ken Lui
Author-email: Ken Lui <116421546+kenlhlui@users.noreply.github.com>
License-Expression: GPL-3.0-or-later
Requires-Dist: httpx>=0.28.1
Requires-Dist: pydantic>=2.12.3
Requires-Dist: tablib[xlsx]>=3.9.0
Requires-Python: >=3.12
Project-URL: Changelog, https://github.com/kenlhlui/pyarchiveit/releases
Project-URL: Documentation, https://kenlhlui.github.io/pyarchiveit/
Project-URL: Homepage, https://kenlhlui.github.io/pyarchiveit/
Project-URL: Repository, https://github.com/kenlhlui/pyarchiveit
